{
	"info": {
		"_postman_id": "67046e0f-010b-47da-833d-27c11a253caa",
		"name": "Spring-Keycloak",
		"schema": "https://schema.getpostman.com/json/collection/v2.1.0/collection.json"
	},
	"item": [
		{
			"name": "Get Students",
			"request": {
				"auth": {
					"type": "oauth2",
					"oauth2": [
						{
							"key": "redirect_uri",
							"value": "localhost:8080",
							"type": "string"
						},
						{
							"key": "useBrowser",
							"value": false,
							"type": "boolean"
						},
						{
							"key": "clientId",
							"value": "user-service",
							"type": "string"
						},
						{
							"key": "accessTokenUrl",
							"value": "http://localhost:8181/realms/university/protocol/openid-connect/token",
							"type": "string"
						},
						{
							"key": "tokenName",
							"value": "prof-auth",
							"type": "string"
						},
						{
							"key": "authUrl",
							"value": "http://localhost:8181/realms/university/protocol/openid-connect/auth",
							"type": "string"
						},
						{
							"key": "addTokenTo",
							"value": "header",
							"type": "string"
						}
					]
				},
				"method": "GET",
				"header": [],
				"url": {
					"raw": "http://localhost:8080/students",
					"protocol": "http",
					"host": [
						"localhost"
					],
					"port": "8080",
					"path": [
						"students"
					]
				}
			},
			"response": []
		},
		{
			"name": "Create Student",
			"request": {
				"auth": {
					"type": "oauth2",
					"oauth2": [
						{
							"key": "redirect_uri",
							"value": "localhost:8080",
							"type": "string"
						},
						{
							"key": "useBrowser",
							"value": false,
							"type": "boolean"
						},
						{
							"key": "clientId",
							"value": "user-service",
							"type": "string"
						},
						{
							"key": "accessTokenUrl",
							"value": "http://localhost:8181/realms/university/protocol/openid-connect/token",
							"type": "string"
						},
						{
							"key": "tokenName",
							"value": "prof-auth",
							"type": "string"
						},
						{
							"key": "authUrl",
							"value": "http://localhost:8181/realms/university/protocol/openid-connect/auth",
							"type": "string"
						},
						{
							"key": "addTokenTo",
							"value": "header",
							"type": "string"
						}
					]
				},
				"method": "POST",
				"header": [],
				"url": {
					"raw": "http://localhost:8080/students",
					"protocol": "http",
					"host": [
						"localhost"
					],
					"port": "8080",
					"path": [
						"students"
					]
				}
			},
			"response": []
		}
	]
}